m23/__init__.py
m23/__main__.py
m23/constants.py
m23/align/__init__.py
m23/calibrate/__init__.py
m23/calibrate/calibration.py
m23/calibrate/master_calibrate.py
m23/charts/__init__.py
m23/coma/__init__.py
m23/combine/__init__.py
m23/exceptions/__init__.py
m23/extract/__init__.py
m23/extract/bg.py
m23/file/__init__.py
m23/file/aligned_combined_file.py
m23/file/alignment_stats_file.py
m23/file/color_normalized_file.py
m23/file/flux_log_combined_file.py
m23/file/log_file_combined_file.py
m23/file/masterflat_file.py
m23/file/normfactor_file.py
m23/file/raw_image_file.py
m23/file/reference_log_file.py
m23/file/ri_color_file.py
m23/file/sky_bg_file.py
m23/internight_normalize/__init__.py
m23/matrix/__init__.py
m23/matrix/crop.py
m23/matrix/fill.py
m23/matrix/region.py
m23/matrix/utils.py
m23/norm/__init__.py
m23/norm/get_line.py
m23/processor/__init__.py
m23/processor/align_combined_extract.py
m23/processor/config_loader.py
m23/processor/generate_masterflat.py
m23/processor/generate_masterflat_config_loader.py
m23/processor/nights_csv.py
m23/processor/nights_csv_config_loader.py
m23/processor/process_nights.py
m23/processor/renormalize.py
m23/processor/renormalize_config_loader.py
m23/reference/08-05-03_m23_3.5-071.txt
m23/reference/MeanRI100.txt
m23/reference/README.md
m23/reference/__init__.py
m23/reference/m23_3.5_071.fit
m23/reference/ref_no_na_w_2509_10.txt
m23/reference/ref_with_new_stars.txt
m23/sky/__init__.py
m23/sky/moon/__init__.py
m23/trans/__init__.py
m23/trans/fits.py
m23/utils/__init__.py
m23/utils/date.py
m23/utils/flux_to_magnitude.py
m23/utils/rename.py
m23-1.24.0.dist-info/METADATA
m23-1.24.0.dist-info/WHEEL
m23-1.24.0.dist-info/RECORD
