Metadata-Version: 2.1
Name: m23
Version: 1.24.0
Requires-Python: >=3.10
Requires-Dist: astroalign==2.4.1
Requires-Dist: astropy==5.2.1
Requires-Dist: ephem==4.1.4
Requires-Dist: matplotlib==3.7.0
Requires-Dist: multiprocess==0.70.14
Requires-Dist: numpy==1.24.2
Requires-Dist: opencv-python==4.7.0.68
Requires-Dist: toml==0.10.2
Requires-Dist: typing-extensions==4.4.0
